datamule/__init__.py
datamule/config.py
datamule/datasets.py
datamule/helper.py
datamule/index.py
datamule/package_updater.py
datamule/book/__init__.py
datamule/book/book.py
datamule/book/download_dataset_from_s3.py
datamule/book/s3transfer.py
datamule/cloud/__init__.py
datamule/data/listed_filer_metadata.csv
datamule/datamule/__init__.py
datamule/datamule/datamule_lookup.py
datamule/datamule/datamule_mysql_rds.py
datamule/datamule/downloader.py
datamule/datamule/sec_connector.py
datamule/datamule/tar_downloader.py
datamule/document/__init__.py
datamule/document/document.py
datamule/filings_constructor/__init__.py
datamule/filings_constructor/filings_constructor.py
datamule/mapping_dicts/__init__.py
datamule/mapping_dicts/html_mapping_dicts.py
datamule/mapping_dicts/xml_mapping_dicts.py
datamule/portfolio/__init__.py
datamule/portfolio/portfolio.py
datamule/portfolio/portfolio_compression_utils_legacy.py
datamule/providers/__init__.py
datamule/providers/providers.py
datamule/sec/__init__.py
datamule/sec/utils.py
datamule/sec/infrastructure/__init__.py
datamule/sec/infrastructure/submissions_metadata.py
datamule/sec/submissions/__init__.py
datamule/sec/submissions/downloader.py
datamule/sec/submissions/eftsquery.py
datamule/sec/submissions/monitor.py
datamule/sec/submissions/streamer.py
datamule/sec/submissions/textsearch.py
datamule/sec/xbrl/__init__.py
datamule/sec/xbrl/downloadcompanyfacts.py
datamule/sec/xbrl/filter_xbrl.py
datamule/sec/xbrl/streamcompanyfacts.py
datamule/sec/xbrl/xbrlmonitor.py
datamule/seclibrary/__init__.py
datamule/seclibrary/bq.py
datamule/sheet/__init__.py
datamule/sheet/sheet.py
datamule/submission/__init__.py
datamule/submission/submission.py
datamule/submission/tar_submission.py
datamule/tables/__init__.py
datamule/tables/tables.py
datamule/tables/tables_13fhr.py
datamule/tables/tables_25nse.py
datamule/tables/tables_informationtable.py
datamule/tables/tables_npx.py
datamule/tables/tables_ownership.py
datamule-3.1.0.dist-info/METADATA
datamule-3.1.0.dist-info/WHEEL
datamule-3.1.0.dist-info/top_level.txt
datamule-3.1.0.dist-info/RECORD
