Metadata-Version: 2.1
Name: datamule
Version: 3.1.0
Summary: Work with SEC submissions at scale.
Home-page: https://github.com/john-friedman/datamule-python
Author: John Friedman
Requires-Dist: aiohttp
Requires-Dist: aiolimiter
Requires-Dist: tqdm
Requires-Dist: requests
Requires-Dist: nest-asyncio
Requires-Dist: aiofiles
Requires-Dist: setuptools
Requires-Dist: selectolax
Requires-Dist: pytz
Requires-Dist: zstandard
Requires-Dist: doc2dict
Requires-Dist: secxbrl
Requires-Dist: secsgml
Requires-Dist: websocket-client
Requires-Dist: company-fundamentals
Requires-Dist: flashtext
Requires-Dist: aioboto3
